os_faults/__init__.py
os_faults/registry.py
os_faults/utils.py
os_faults/ansible/__init__.py
os_faults/ansible/executor.py
os_faults/ansible/modules/__init__.py
os_faults/ansible/modules/freeze.py
os_faults/ansible/modules/kill.py
os_faults/ansible/modules/stress.py
os_faults/api/__init__.py
os_faults/api/base_driver.py
os_faults/api/cloud_management.py
os_faults/api/container.py
os_faults/api/error.py
os_faults/api/human.py
os_faults/api/node_collection.py
os_faults/api/node_discover.py
os_faults/api/power_management.py
os_faults/api/service.py
os_faults/api/utils.py
os_faults/cmd/__init__.py
os_faults/cmd/cmd.py
os_faults/cmd/main.py
os_faults/drivers/__init__.py
os_faults/drivers/shared_schemas.py
os_faults/drivers/cloud/__init__.py
os_faults/drivers/cloud/devstack.py
os_faults/drivers/cloud/saltcloud.py
os_faults/drivers/cloud/universal.py
os_faults/drivers/containers/__init__.py
os_faults/drivers/containers/docker.py
os_faults/drivers/nodes/__init__.py
os_faults/drivers/nodes/node_list.py
os_faults/drivers/power/__init__.py
os_faults/drivers/power/ipmi.py
os_faults/drivers/power/libvirt.py
os_faults/drivers/services/__init__.py
os_faults/drivers/services/process.py
os_faults/drivers/services/salt.py
os_faults/drivers/services/system.py
os_faults/tests/__init__.py
os_faults/tests/devstack/__init__.py
os_faults/tests/devstack/os-faults-devstack.yaml
os_faults/tests/devstack/os-faults-universal.yaml
os_faults/tests/devstack/test_lib.py
os_faults/tests/devstack/test_os_inject_fault.py
os_faults/tests/devstack/playbooks/post.yml
os_faults/tests/devstack/playbooks/pre.yml
os_faults/tests/devstack/playbooks/run_on_devstack.yml
os_faults/tests/unit/__init__.py
os_faults/tests/unit/fakes.py
os_faults/tests/unit/test.py
os_faults/tests/unit/test_os_faults.py
os_faults/tests/unit/test_registry.py
os_faults/tests/unit/test_utils.py
os_faults/tests/unit/ansible/__init__.py
os_faults/tests/unit/ansible/test_executor.py
os_faults/tests/unit/api/__init__.py
os_faults-0.3.0.dist-info/AUTHORS
os_faults-0.3.0.dist-info/LICENSE
os_faults-0.3.0.dist-info/METADATA
os_faults-0.3.0.dist-info/WHEEL
os_faults-0.3.0.dist-info/entry_points.txt
os_faults-0.3.0.dist-info/pbr.json
os_faults-0.3.0.dist-info/top_level.txt
os_faults-0.3.0.dist-info/RECORD
