Metadata-Version: 2.1
Name: os-faults
Version: 0.3.0
Summary: OpenStack fault-injection library
Home-page: http://os-faults.readthedocs.io/
Author: OpenStack
Author-email: openstack-discuss@lists.openstack.org
License: UNKNOWN
Download-URL: https://pypi.org/project/os-faults/
Project-URL: Bug Tracker, https://bugs.launchpad.net/os-faults
Project-URL: Documentation, http://os-faults.readthedocs.io/
Project-URL: Source Code, https://opendev.org/performa/os-faults/
Platform: UNKNOWN
Classifier: Environment :: OpenStack
Classifier: Intended Audience :: Information Technology
Classifier: Intended Audience :: System Administrators
Classifier: License :: OSI Approved :: Apache Software License
Classifier: Operating System :: POSIX :: Linux
Classifier: Programming Language :: Python
Classifier: Programming Language :: Python :: 3
Classifier: Programming Language :: Python :: 3.8
Classifier: Programming Language :: Python :: 3.9
Classifier: Programming Language :: Python :: 3.10
Classifier: Programming Language :: Python :: 3.11
Requires-Python: >=3.8
Requires-Dist: PyYAML (>=3.10.0)
Requires-Dist: click (>=6.7)
Requires-Dist: iso8601 (>=0.1.11)
Requires-Dist: jsonschema (>=2.6.0)
Requires-Dist: oslo.concurrency (>=3.0.0)
Requires-Dist: oslo.i18n (>=2.1.0)
Requires-Dist: oslo.serialization (>=1.10.0)
Requires-Dist: oslo.utils (>=3.20.0)
Requires-Dist: pbr (>=2.0.0)
Requires-Dist: platformdirs (>=2.6.0)
Requires-Dist: pyghmi (>=1.0.9)
